simple_llm_api/__init__.py
simple_llm_api/exceptions.py
simple_llm_api/main.py
simple_llm_api-1.3.1.dist-info/licenses/LICENSE
simple_llm_api-1.3.1.dist-info/METADATA
simple_llm_api-1.3.1.dist-info/WHEEL
simple_llm_api-1.3.1.dist-info/top_level.txt
simple_llm_api-1.3.1.dist-info/RECORD
