Metadata-Version: 2.4
Name: simple-llm-api
Version: 1.3.1
Summary: A simple and easy-to-use LLM API Wrapper
Author-email: Ahmet Burhan Kayalı <ahmetburhan1703@gmail.com>
Project-URL: Homepage, https://github.com/SoAp9035/simple-llm-api
Project-URL: Bug Tracker, https://github.com/SoAp9035/simple-llm-api/issues
Keywords: simple,llm,openai,anthropic,gemini,mistral,deepseek,api,wrapper
Classifier: Intended Audience :: Developers
Classifier: Intended Audience :: Science/Research
Classifier: Topic :: Software Development :: Libraries :: Python Modules
Classifier: Topic :: Internet :: WWW/HTTP
Classifier: License :: OSI Approved :: MIT License
License-File: LICENSE
Requires-Dist: requests>=2.32.5
Dynamic: license-file
